{
  "_class": "shapePath",
  "booleanOperation": -1,
  "do_objectID": "30F3EA1E-F59F-4F39-9DA1-7B8EF15CE8DB",
  "edited": true,
  "exportOptions": {
    "_class": "exportOptions",
    "exportFormats": [
    ],
    "includedLayerIds": [
    ],
    "layerOptions": 0,
    "shouldTrim": false
  },
  "frame": {
    "_class": "rect",
    "constrainProportions": false,
    "height": 1.863850611043063,
    "width": 2.491152375201153,
    "x": 77.4755133840232,
    "y": 109.5847807796616
  },
  "isFlippedHorizontal": false,
  "isFlippedVertical": false,
  "isLocked": false,
  "isVisible": true,
  "layerListExpandedType": 0,
  "name": "Path",
  "nameIsFixed": false,
  "path": {
    "_class": "path",
    "isClosed": true,
    "pointRadiusBehaviour": 1,
    "points": [
      {
        "_class": "curvePoint",
        "cornerRadius": 0,
        "curveFrom": "{0.10655737704918093, 0.21704483453149948}",
        "curveMode": 4,
        "curveTo": "{0, 4.4834531500725916e-05}",
        "hasCurveFrom": true,
        "hasCurveTo": false,
        "point": "{0, 4.4834531500725916e-05}"
      },
      {
        "_class": "curvePoint",
        "cornerRadius": 0,
        "curveFrom": "{0.43964232488822946, 0.67604483453148845}",
        "curveMode": 4,
        "curveTo": "{0.21087928464977759, 0.42704483453149322}",
        "hasCurveFrom": true,
        "hasCurveTo": true,
        "point": "{0.30998509687034598, 0.62404483453149595}"
      },
      {
        "_class": "curvePoint",
        "cornerRadius": 0,
        "curveFrom": "{0.77272727272727804, 0.81204483453149834}",
        "curveMode": 3,
        "curveTo": "{0.55439642324888261, 0.72204483453149493}",
        "hasCurveFrom": true,
        "hasCurveTo": true,
        "point": "{0.66840536512668136, 0.76904483453150618}"
      },
      {
        "_class": "curvePoint",
        "cornerRadius": 0,
        "curveFrom": "{0.87481371087929038, 0.14304483453150141}",
        "curveMode": 4,
        "curveTo": "{0.88077496274217826, 0.85704483453150004}",
        "hasCurveFrom": true,
        "hasCurveTo": true,
        "point": "{1, 0.9070448345314972}"
      },
      {
        "_class": "curvePoint",
        "cornerRadius": 0,
        "curveFrom": "{0, 4.4834531500725916e-05}",
        "curveMode": 4,
        "curveTo": "{0.53278688524590467, -0.0029551654684993878}",
        "hasCurveFrom": false,
        "hasCurveTo": true,
        "point": "{0, 4.4834531500725916e-05}"
      }
    ]
  },
  "resizingConstraint": 63,
  "resizingType": 0,
  "rotation": 0,
  "shouldBreakMaskChain": false
}