{
  "_class": "group",
  "do_objectID": "62F3D77C-2756-4578-BCB4-7F25B92B831B",
  "exportOptions": {
    "_class": "exportOptions",
    "exportFormats": [
    ],
    "includedLayerIds": [
    ],
    "layerOptions": 0,
    "shouldTrim": false
  },
  "frame": {
    "_class": "rect",
    "constrainProportions": true,
    "height": 90,
    "width": 90,
    "x": 6,
    "y": 6
  },
  "hasClickThrough": false,
  "isFlippedHorizontal": false,
  "isFlippedVertical": false,
  "isLocked": false,
  "isVisible": true,
  "layerListExpandedType": 2,
  "layers": [
    {
      "class": "shapeGroup",
      "id": "98FF55F0-889D-47F0-9E77-634F6CF2DBB3"
    },
    {
      "class": "bitmap",
      "id": "742DF007-B72C-4CA2-9D30-516634E5B30E"
    },
    {
      "class": "shapeGroup",
      "id": "D874EFF5-97E7-4531-91F9-E5BB1E42A360"
    }
  ],
  "name": "螢幕快照 2017-10-25 下午9.32.48",
  "nameIsFixed": false,
  "resizingConstraint": 63,
  "resizingType": 0,
  "rotation": 0,
  "shouldBreakMaskChain": false,
  "style": {
    "_class": "style",
    "blur": {
      "_class": "blur",
      "center": "{0.5, 0.5}",
      "isEnabled": false,
      "motionAngle": 0,
      "radius": 6.915861868529471,
      "type": 0
    },
    "endDecorationType": 0,
    "miterLimit": 10,
    "startDecorationType": 0
  }
}