{
  "_class": "group",
  "do_objectID": "503392F0-EF7C-40CD-AFC0-3845F7E04FA7",
  "exportOptions": {
    "_class": "exportOptions",
    "exportFormats": [
    ],
    "includedLayerIds": [
    ],
    "layerOptions": 0,
    "shouldTrim": false
  },
  "frame": {
    "_class": "rect",
    "constrainProportions": false,
    "height": 43,
    "width": 43,
    "x": 413,
    "y": 694
  },
  "hasClickThrough": false,
  "isFlippedHorizontal": false,
  "isFlippedVertical": false,
  "isLocked": false,
  "isVisible": true,
  "layerListExpandedType": 1,
  "layers": [
    {
      "class": "shapeGroup",
      "id": "1D4C41C6-0D20-4B6A-9E12-BC409AFCE8CF"
    },
    {
      "class": "group",
      "id": "D612D3BA-6492-4AA9-B7D8-84AE34832FDA"
    }
  ],
  "name": "Group 5",
  "nameIsFixed": false,
  "resizingConstraint": 36,
  "resizingType": 0,
  "rotation": 0,
  "shouldBreakMaskChain": false,
  "style": {
    "_class": "style",
    "endDecorationType": 0,
    "miterLimit": 10,
    "startDecorationType": 0
  }
}