{
  "_class": "group",
  "do_objectID": "F618A306-70C8-4C23-B8A7-0C7FAF603EDD",
  "exportOptions": {
    "_class": "exportOptions",
    "exportFormats": [
    ],
    "includedLayerIds": [
    ],
    "layerOptions": 0,
    "shouldTrim": false
  },
  "frame": {
    "_class": "rect",
    "constrainProportions": false,
    "height": 43,
    "width": 43,
    "x": 0,
    "y": 0
  },
  "hasClickThrough": false,
  "isFlippedHorizontal": false,
  "isFlippedVertical": false,
  "isLocked": false,
  "isVisible": true,
  "layerListExpandedType": 1,
  "layers": [
    {
      "class": "shapeGroup",
      "id": "D4AE221D-9BD7-4AD5-BFE8-BF67DCCE8F7C"
    },
    {
      "class": "group",
      "id": "B63F2F13-638F-459B-8D08-F961FBE2E448"
    }
  ],
  "name": "Group 5",
  "nameIsFixed": false,
  "resizingConstraint": 9,
  "resizingType": 0,
  "rotation": 0,
  "shouldBreakMaskChain": false,
  "style": {
    "_class": "style",
    "endDecorationType": 0,
    "miterLimit": 10,
    "startDecorationType": 0
  }
}