{
  "_class": "group",
  "do_objectID": "A7DAEB21-A288-47DA-887B-AA3CF0A7F7B9",
  "exportOptions": {
    "_class": "exportOptions",
    "exportFormats": [
    ],
    "includedLayerIds": [
    ],
    "layerOptions": 0,
    "shouldTrim": false
  },
  "frame": {
    "_class": "rect",
    "constrainProportions": false,
    "height": 112,
    "width": 413,
    "x": 52,
    "y": 221
  },
  "hasClickThrough": false,
  "isFlippedHorizontal": false,
  "isFlippedVertical": false,
  "isLocked": false,
  "isVisible": true,
  "layerListExpandedType": 2,
  "layers": [
    {
      "class": "shapeGroup",
      "id": "8E07D110-657E-414F-B550-AE4A863BACC9"
    },
    {
      "class": "bitmap",
      "id": "DDD0DA1A-AC86-4E54-BD09-BE253134F407"
    }
  ],
  "name": "螢幕快照 2017-10-30 下午2.24.47",
  "nameIsFixed": false,
  "resizingConstraint": 63,
  "resizingType": 0,
  "rotation": 0,
  "shouldBreakMaskChain": false,
  "style": {
    "_class": "style",
    "endDecorationType": 0,
    "miterLimit": 10,
    "startDecorationType": 0
  }
}