{
  "_class": "shapePath",
  "booleanOperation": -1,
  "do_objectID": "62394ACE-8504-4438-8E50-0CFF5D3A61E2",
  "edited": true,
  "exportOptions": {
    "_class": "exportOptions",
    "exportFormats": [
    ],
    "includedLayerIds": [
    ],
    "layerOptions": 0,
    "shouldTrim": false
  },
  "frame": {
    "_class": "rect",
    "constrainProportions": false,
    "height": 1.251147368421069,
    "width": 3.749779735682779,
    "x": 1.251488986784124,
    "y": 1.252321052631602
  },
  "isFlippedHorizontal": false,
  "isFlippedVertical": false,
  "isLocked": false,
  "isVisible": true,
  "layerListExpandedType": 0,
  "name": "Path",
  "nameIsFixed": false,
  "path": {
    "_class": "path",
    "isClosed": true,
    "pointRadiusBehaviour": 1,
    "points": [
      {
        "_class": "curvePoint",
        "cornerRadius": 0,
        "curveFrom": "{1, 1}",
        "curveMode": 1,
        "curveTo": "{1, 1}",
        "hasCurveFrom": false,
        "hasCurveTo": false,
        "point": "{1, 1}"
      },
      {
        "_class": "curvePoint",
        "cornerRadius": 0,
        "curveFrom": "{1, 0.1125703564727932}",
        "curveMode": 4,
        "curveTo": "{1, 0.24953095684802862}",
        "hasCurveFrom": true,
        "hasCurveTo": false,
        "point": "{1, 0.24953095684802862}"
      },
      {
        "_class": "curvePoint",
        "cornerRadius": 0,
        "curveFrom": "{0.91656249999999917, 0}",
        "curveMode": 4,
        "curveTo": "{0.9625000000000008, 0}",
        "hasCurveFrom": false,
        "hasCurveTo": true,
        "point": "{0.91656249999999917, 0}"
      },
      {
        "_class": "curvePoint",
        "cornerRadius": 0,
        "curveFrom": "{0.037500000000001386, 0}",
        "curveMode": 4,
        "curveTo": "{0.0831250000000016, 0}",
        "hasCurveFrom": true,
        "hasCurveTo": false,
        "point": "{0.0831250000000016, 0}"
      },
      {
        "_class": "curvePoint",
        "cornerRadius": 0,
        "curveFrom": "{0, 0.24953095684802862}",
        "curveMode": 4,
        "curveTo": "{0, 0.1125703564727932}",
        "hasCurveFrom": false,
        "hasCurveTo": true,
        "point": "{0, 0.24953095684802862}"
      },
      {
        "_class": "curvePoint",
        "cornerRadius": 0,
        "curveFrom": "{0, 1}",
        "curveMode": 1,
        "curveTo": "{0, 1}",
        "hasCurveFrom": false,
        "hasCurveTo": false,
        "point": "{0, 1}"
      }
    ]
  },
  "resizingConstraint": 63,
  "resizingType": 0,
  "rotation": 0,
  "shouldBreakMaskChain": false
}