{
  "_class": "group",
  "do_objectID": "B2796D1A-656D-4F9F-AF01-E8A8ED35EA84",
  "exportOptions": {
    "_class": "exportOptions",
    "exportFormats": [
    ],
    "includedLayerIds": [
    ],
    "layerOptions": 0,
    "shouldTrim": false
  },
  "frame": {
    "_class": "rect",
    "constrainProportions": false,
    "height": 68,
    "width": 68,
    "x": 1061,
    "y": 474
  },
  "hasClickThrough": false,
  "isFlippedHorizontal": false,
  "isFlippedVertical": false,
  "isLocked": false,
  "isVisible": true,
  "layerListExpandedType": 0,
  "layers": [
    {
      "class": "shapeGroup",
      "id": "576A13A4-9F27-4EAB-91E9-6E19BE721D5E"
    },
    {
      "class": "text",
      "id": "481B8D9C-090A-4821-A5C5-406498581551"
    }
  ],
  "name": "Group 4 Copy",
  "nameIsFixed": false,
  "resizingConstraint": 63,
  "resizingType": 0,
  "rotation": 8,
  "shouldBreakMaskChain": false,
  "style": {
    "_class": "style",
    "endDecorationType": 0,
    "miterLimit": 10,
    "startDecorationType": 0
  }
}