{
  "_class": "group",
  "do_objectID": "F4CE0FAB-573F-46C7-A342-F9C8193B3B2B",
  "exportOptions": {
    "_class": "exportOptions",
    "exportFormats": [
    ],
    "includedLayerIds": [
    ],
    "layerOptions": 0,
    "shouldTrim": false
  },
  "frame": {
    "_class": "rect",
    "constrainProportions": false,
    "height": 125,
    "width": 243,
    "x": 90,
    "y": 778
  },
  "hasClickThrough": false,
  "isFlippedHorizontal": false,
  "isFlippedVertical": false,
  "isLocked": false,
  "isVisible": true,
  "layerListExpandedType": 0,
  "layers": [
    {
      "class": "shapeGroup",
      "id": "C06B4BFC-9D25-417C-8178-312CEABCE0A6"
    },
    {
      "class": "text",
      "id": "81EECB00-936B-460C-88A3-903A45E27574"
    },
    {
      "class": "text",
      "id": "460D072C-6E37-4C9F-8E88-437766A1715E"
    },
    {
      "class": "group",
      "id": "0DB9F482-7EED-4FEF-8BE8-A9A50B243396"
    },
    {
      "class": "group",
      "id": "6D07266E-5CC9-4FC6-B2B9-FB0F51C0EB71"
    }
  ],
  "name": "Group 3 Copy 10",
  "nameIsFixed": false,
  "resizingConstraint": 63,
  "resizingType": 0,
  "rotation": 0,
  "shouldBreakMaskChain": false,
  "style": {
    "_class": "style",
    "endDecorationType": 0,
    "miterLimit": 10,
    "startDecorationType": 0
  }
}